pyperfmon/__init__.py
pyperfmon/pyperfmon.py
pyperfmon-0.2.2.1.dist-info/LICENSE
pyperfmon-0.2.2.1.dist-info/METADATA
pyperfmon-0.2.2.1.dist-info/WHEEL
pyperfmon-0.2.2.1.dist-info/top_level.txt
pyperfmon-0.2.2.1.dist-info/RECORD
