Metadata-Version: 2.1
Name: pyperfmon
Version: 0.2.2.1
Summary: pyperfmon
Home-page: https://github.com/damies13/pyperfmon
Author: damies13
Author-email: damies13+pyperfmon@gmail.com
License: UNKNOWN
Project-URL: Getting Help, https://github.com/damies13/pyperfmon
Project-URL: Source, https://github.com/damies13/pyperfmon
Platform: UNKNOWN
Classifier: Development Status :: 4 - Beta
Classifier: Topic :: System :: Monitoring
Classifier: Programming Language :: Python :: 3.6
Classifier: License :: OSI Approved :: GNU General Public License v3 (GPLv3)
Classifier: Operating System :: Microsoft :: Windows 
Requires-Python: >=3.6
License-File: LICENSE
Requires-Dist: wmi
